Workbook

Sheet 💙 Comece aqui
B2: 🐷 Planejador Financeiro Anual — Estúdio Planifica
B3: Controle financeiro fofo, simples e do jeitinho que você merece 💙
B5: 📝 Como usar
B6: 1️⃣ Escolha o mês | C6: Clique na aba do mês lá embaixo (Janeiro, Fevereiro...).
B7: 2️⃣ Preencha suas entradas | C7: Na tabela 💰 Entradas, coloque nome, dia e valor do que você recebe.
B8: 3️⃣ Registre os gastos | C8: Use 🏠 Contas Fixas (aluguel, luz) e 🛒 Despesas Variáveis (mercado, lazer).
B9: 4️⃣ Anote as economias | C9: Em 💎 Economias, registre o que está guardando ou investindo.
B10: 5️⃣ Veja o Cofrinho reagir! | C10: O porquinho muda de humor conforme o seu saldo do mês 🐷
B11: 6️⃣ Acompanhe os gráficos | C11: Eles mostram sozinhos para onde vai o seu dinheiro.
B13: 🐷 Como o Cofrinho reage
B14: 🤑 Cofrinho rico | C14: Disponível acima de R$ 1.000 — você arrasou este mês!
B15: 🐷 Cofrinho tranquilo | C15: Disponível entre R$ 0 e R$ 1.000 — atenção aos gastos.
B16: 😰 Cofrinho preocupado | C16: Disponível negativo — você gastou mais do que ganhou.
B18: 📅 Resumo do Ano
B19: Veja tudo junto | C19: A aba "📅 Resumo do Ano" soma os 12 meses automaticamente. Não precisa mexer.
B21: ⚠️ Dica: preencha só as colunas Nome, Dia e Valor. Os totais, o Cofrinho e os gráficos são automáticos — não apague as fórmulas 💙

Sheet Janeiro
B2: 🐷 Estúdio Planifica • Janeiro | T2: ▼ dados dos gráficos (não apague)
B4: ENTRADAS TOTAIS | E4: DESPESAS TOTAIS | H4: ECONOMIAS | K4: DISPONÍVEL | N4: =IF(K5>1000,"🤑",IF(K5>=0,"🐷","😰")) | T4: Entradas | U4: =D29
B5: =D29 | E5: =G29+J29 | H5: =M29 | K5: =D29-G29-J29-M29 | T5: Contas Fixas | U5: =G29
T6: Desp. Variáveis | U6: =J29
N7: =IF(K5>1000,"Cofrinho tá cheio! 💰",IF(K5>=0,"No azul — de olho nos gastos 👀","Ops! Gastou mais do que ganhou 😥")) | T7: Economias | U7: =M29
B10: 💰 Entradas | E10: 🏠 Contas Fixas | H10: 🛒 Despesas Variáveis | K10: 💎 Economias | T10: Entradas | U10: =B5
B11: Nome | C11: Dia | D11: Valor | E11: Nome | F11: Dia | G11: Valor | H11: Nome | I11: Dia | J11: Valor | K11: Nome | L11: Dia | M11: Valor | T11: Despesas | U11: =E5
B12: Salário | C12: 5 | D12: 3000 | E12: Aluguel | F12: 10 | G12: 1200 | H12: Supermercado | I12: 20 | J12: 600 | K12: Reserva de emergência | L12: 30 | M12: 400 | T12: Disponível | U12: =K5
B13: Freela / renda extra | C13: 15 | D13: 500 | E13: Internet | F13: 15 | G13: 100 | H13: Farmácia | I13: 12 | J13: 80
B29: TOTAL | D29: =SUM(D12:D28) | E29: TOTAL | G29: =SUM(G12:G28) | H29: TOTAL | J29: =SUM(J12:J28) | K29: TOTAL | M29: =SUM(M12:M28)

Sheet Fevereiro
B2: 🐷 Estúdio Planifica • Fevereiro | T2: ▼ dados dos gráficos (não apague)
B4: ENTRADAS TOTAIS | E4: DESPESAS TOTAIS | H4: ECONOMIAS | K4: DISPONÍVEL | N4: =IF(K5>1000,"🤑",IF(K5>=0,"🐷","😰")) | T4: Entradas | U4: =D29
B5: =D29 | E5: =G29+J29 | H5: =M29 | K5: =D29-G29-J29-M29 | T5: Contas Fixas | U5: =G29
T6: Desp. Variáveis | U6: =J29
N7: =IF(K5>1000,"Cofrinho tá cheio! 💰",IF(K5>=0,"No azul — de olho nos gastos 👀","Ops! Gastou mais do que ganhou 😥")) | T7: Economias | U7: =M29
B10: 💰 Entradas | E10: 🏠 Contas Fixas | H10: 🛒 Despesas Variáveis | K10: 💎 Economias | T10: Entradas | U10: =B5
B11: Nome | C11: Dia | D11: Valor | E11: Nome | F11: Dia | G11: Valor | H11: Nome | I11: Dia | J11: Valor | K11: Nome | L11: Dia | M11: Valor | T11: Despesas | U11: =E5
B12: Salário | C12: 5 | D12: 3000 | E12: Aluguel | F12: 10 | G12: 1200 | H12: Supermercado | I12: 20 | J12: 600 | K12: Reserva de emergência | L12: 30 | M12: 400 | T12: Disponível | U12: =K5
B13: Freela / renda extra | C13: 15 | D13: 500 | E13: Internet | F13: 15 | G13: 100 | H13: Farmácia | I13: 12 | J13: 80
B29: TOTAL | D29: =SUM(D12:D28) | E29: TOTAL | G29: =SUM(G12:G28) | H29: TOTAL | J29: =SUM(J12:J28) | K29: TOTAL | M29: =SUM(M12:M28)

Sheet Março
B2: 🐷 Estúdio Planifica • Março | T2: ▼ dados dos gráficos (não apague)
B4: ENTRADAS TOTAIS | E4: DESPESAS TOTAIS | H4: ECONOMIAS | K4: DISPONÍVEL | N4: =IF(K5>1000,"🤑",IF(K5>=0,"🐷","😰")) | T4: Entradas | U4: =D29
B5: =D29 | E5: =G29+J29 | H5: =M29 | K5: =D29-G29-J29-M29 | T5: Contas Fixas | U5: =G29
T6: Desp. Variáveis | U6: =J29
N7: =IF(K5>1000,"Cofrinho tá cheio! 💰",IF(K5>=0,"No azul — de olho nos gastos 👀","Ops! Gastou mais do que ganhou 😥")) | T7: Economias | U7: =M29
B10: 💰 Entradas | E10: 🏠 Contas Fixas | H10: 🛒 Despesas Variáveis | K10: 💎 Economias | T10: Entradas | U10: =B5
B11: Nome | C11: Dia | D11: Valor | E11: Nome | F11: Dia | G11: Valor | H11: Nome | I11: Dia | J11: Valor | K11: Nome | L11: Dia | M11: Valor | T11: Despesas | U11: =E5
B12: Salário | C12: 5 | D12: 3000 | E12: Aluguel | F12: 10 | G12: 1200 | H12: Supermercado | I12: 20 | J12: 600 | K12: Reserva de emergência | L12: 30 | M12: 400 | T12: Disponível | U12: =K5
B13: Freela / renda extra | C13: 15 | D13: 500 | E13: Internet | F13: 15 | G13: 100 | H13: Farmácia | I13: 12 | J13: 80
B29: TOTAL | D29: =SUM(D12:D28) | E29: TOTAL | G29: =SUM(G12:G28) | H29: TOTAL | J29: =SUM(J12:J28) | K29: TOTAL | M29: =SUM(M12:M28)

Sheet Abril
B2: 🐷 Estúdio Planifica • Abril | T2: ▼ dados dos gráficos (não apague)
B4: ENTRADAS TOTAIS | E4: DESPESAS TOTAIS | H4: ECONOMIAS | K4: DISPONÍVEL | N4: =IF(K5>1000,"🤑",IF(K5>=0,"🐷","😰")) | T4: Entradas | U4: =D29
B5: =D29 | E5: =G29+J29 | H5: =M29 | K5: =D29-G29-J29-M29 | T5: Contas Fixas | U5: =G29
T6: Desp. Variáveis | U6: =J29
N7: =IF(K5>1000,"Cofrinho tá cheio! 💰",IF(K5>=0,"No azul — de olho nos gastos 👀","Ops! Gastou mais do que ganhou 😥")) | T7: Economias | U7: =M29
B10: 💰 Entradas | E10: 🏠 Contas Fixas | H10: 🛒 Despesas Variáveis | K10: 💎 Economias | T10: Entradas | U10: =B5
B11: Nome | C11: Dia | D11: Valor | E11: Nome | F11: Dia | G11: Valor | H11: Nome | I11: Dia | J11: Valor | K11: Nome | L11: Dia | M11: Valor | T11: Despesas | U11: =E5
B12: Salário | C12: 5 | D12: 3000 | E12: Aluguel | F12: 10 | G12: 1200 | H12: Supermercado | I12: 20 | J12: 600 | K12: Reserva de emergência | L12: 30 | M12: 400 | T12: Disponível | U12: =K5
B13: Freela / renda extra | C13: 15 | D13: 500 | E13: Internet | F13: 15 | G13: 100 | H13: Farmácia | I13: 12 | J13: 80
B29: TOTAL | D29: =SUM(D12:D28) | E29: TOTAL | G29: =SUM(G12:G28) | H29: TOTAL | J29: =SUM(J12:J28) | K29: TOTAL | M29: =SUM(M12:M28)

Sheet Maio
B2: 🐷 Estúdio Planifica • Maio | T2: ▼ dados dos gráficos (não apague)
B4: ENTRADAS TOTAIS | E4: DESPESAS TOTAIS | H4: ECONOMIAS | K4: DISPONÍVEL | N4: =IF(K5>1000,"🤑",IF(K5>=0,"🐷","😰")) | T4: Entradas | U4: =D29
B5: =D29 | E5: =G29+J29 | H5: =M29 | K5: =D29-G29-J29-M29 | T5: Contas Fixas | U5: =G29
T6: Desp. Variáveis | U6: =J29
N7: =IF(K5>1000,"Cofrinho tá cheio! 💰",IF(K5>=0,"No azul — de olho nos gastos 👀","Ops! Gastou mais do que ganhou 😥")) | T7: Economias | U7: =M29
B10: 💰 Entradas | E10: 🏠 Contas Fixas | H10: 🛒 Despesas Variáveis | K10: 💎 Economias | T10: Entradas | U10: =B5
B11: Nome | C11: Dia | D11: Valor | E11: Nome | F11: Dia | G11: Valor | H11: Nome | I11: Dia | J11: Valor | K11: Nome | L11: Dia | M11: Valor | T11: Despesas | U11: =E5
B12: Salário | C12: 5 | D12: 3000 | E12: Aluguel | F12: 10 | G12: 1200 | H12: Supermercado | I12: 20 | J12: 600 | K12: Reserva de emergência | L12: 30 | M12: 400 | T12: Disponível | U12: =K5
B13: Freela / renda extra | C13: 15 | D13: 500 | E13: Internet | F13: 15 | G13: 100 | H13: Farmácia | I13: 12 | J13: 80
B29: TOTAL | D29: =SUM(D12:D28) | E29: TOTAL | G29: =SUM(G12:G28) | H29: TOTAL | J29: =SUM(J12:J28) | K29: TOTAL | M29: =SUM(M12:M28)

Sheet Junho
B2: 🐷 Estúdio Planifica • Junho | T2: ▼ dados dos gráficos (não apague)
B4: ENTRADAS TOTAIS | E4: DESPESAS TOTAIS | H4: ECONOMIAS | K4: DISPONÍVEL | N4: =IF(K5>1000,"🤑",IF(K5>=0,"🐷","😰")) | T4: Entradas | U4: =D29
B5: =D29 | E5: =G29+J29 | H5: =M29 | K5: =D29-G29-J29-M29 | T5: Contas Fixas | U5: =G29
T6: Desp. Variáveis | U6: =J29
N7: =IF(K5>1000,"Cofrinho tá cheio! 💰",IF(K5>=0,"No azul — de olho nos gastos 👀","Ops! Gastou mais do que ganhou 😥")) | T7: Economias | U7: =M29
B10: 💰 Entradas | E10: 🏠 Contas Fixas | H10: 🛒 Despesas Variáveis | K10: 💎 Economias | T10: Entradas | U10: =B5
B11: Nome | C11: Dia | D11: Valor | E11: Nome | F11: Dia | G11: Valor | H11: Nome | I11: Dia | J11: Valor | K11: Nome | L11: Dia | M11: Valor | T11: Despesas | U11: =E5
B12: Salário | C12: 5 | D12: 3000 | E12: Aluguel | F12: 10 | G12: 1200 | H12: Supermercado | I12: 20 | J12: 600 | K12: Reserva de emergência | L12: 30 | M12: 400 | T12: Disponível | U12: =K5
B13: Freela / renda extra | C13: 15 | D13: 500 | E13: Internet | F13: 15 | G13: 100 | H13: Farmácia | I13: 12 | J13: 80
B29: TOTAL | D29: =SUM(D12:D28) | E29: TOTAL | G29: =SUM(G12:G28) | H29: TOTAL | J29: =SUM(J12:J28) | K29: TOTAL | M29: =SUM(M12:M28)

Sheet Julho
B2: 🐷 Estúdio Planifica • Julho | T2: ▼ dados dos gráficos (não apague)
B4: ENTRADAS TOTAIS | E4: DESPESAS TOTAIS | H4: ECONOMIAS | K4: DISPONÍVEL | N4: =IF(K5>1000,"🤑",IF(K5>=0,"🐷","😰")) | T4: Entradas | U4: =D29
B5: =D29 | E5: =G29+J29 | H5: =M29 | K5: =D29-G29-J29-M29 | T5: Contas Fixas | U5: =G29
T6: Desp. Variáveis | U6: =J29
N7: =IF(K5>1000,"Cofrinho tá cheio! 💰",IF(K5>=0,"No azul — de olho nos gastos 👀","Ops! Gastou mais do que ganhou 😥")) | T7: Economias | U7: =M29
B10: 💰 Entradas | E10: 🏠 Contas Fixas | H10: 🛒 Despesas Variáveis | K10: 💎 Economias | T10: Entradas | U10: =B5
B11: Nome | C11: Dia | D11: Valor | E11: Nome | F11: Dia | G11: Valor | H11: Nome | I11: Dia | J11: Valor | K11: Nome | L11: Dia | M11: Valor | T11: Despesas | U11: =E5
B12: Salário | C12: 5 | D12: 3000 | E12: Aluguel | F12: 10 | G12: 1200 | H12: Supermercado | I12: 20 | J12: 600 | K12: Reserva de emergência | L12: 30 | M12: 400 | T12: Disponível | U12: =K5
B13: Freela / renda extra | C13: 15 | D13: 500 | E13: Internet | F13: 15 | G13: 100 | H13: Farmácia | I13: 12 | J13: 80
B29: TOTAL | D29: =SUM(D12:D28) | E29: TOTAL | G29: =SUM(G12:G28) | H29: TOTAL | J29: =SUM(J12:J28) | K29: TOTAL | M29: =SUM(M12:M28)

Sheet Agosto
B2: 🐷 Estúdio Planifica • Agosto | T2: ▼ dados dos gráficos (não apague)
B4: ENTRADAS TOTAIS | E4: DESPESAS TOTAIS | H4: ECONOMIAS | K4: DISPONÍVEL | N4: =IF(K5>1000,"🤑",IF(K5>=0,"🐷","😰")) | T4: Entradas | U4: =D29
B5: =D29 | E5: =G29+J29 | H5: =M29 | K5: =D29-G29-J29-M29 | T5: Contas Fixas | U5: =G29
T6: Desp. Variáveis | U6: =J29
N7: =IF(K5>1000,"Cofrinho tá cheio! 💰",IF(K5>=0,"No azul — de olho nos gastos 👀","Ops! Gastou mais do que ganhou 😥")) | T7: Economias | U7: =M29
B10: 💰 Entradas | E10: 🏠 Contas Fixas | H10: 🛒 Despesas Variáveis | K10: 💎 Economias | T10: Entradas | U10: =B5
B11: Nome | C11: Dia | D11: Valor | E11: Nome | F11: Dia | G11: Valor | H11: Nome | I11: Dia | J11: Valor | K11: Nome | L11: Dia | M11: Valor | T11: Despesas | U11: =E5
B12: Salário | C12: 5 | D12: 3000 | E12: Aluguel | F12: 10 | G12: 1200 | H12: Supermercado | I12: 20 | J12: 600 | K12: Reserva de emergência | L12: 30 | M12: 400 | T12: Disponível | U12: =K5
B13: Freela / renda extra | C13: 15 | D13: 500 | E13: Internet | F13: 15 | G13: 100 | H13: Farmácia | I13: 12 | J13: 80
B29: TOTAL | D29: =SUM(D12:D28) | E29: TOTAL | G29: =SUM(G12:G28) | H29: TOTAL | J29: =SUM(J12:J28) | K29: TOTAL | M29: =SUM(M12:M28)

Sheet Setembro
B2: 🐷 Estúdio Planifica • Setembro | T2: ▼ dados dos gráficos (não apague)
B4: ENTRADAS TOTAIS | E4: DESPESAS TOTAIS | H4: ECONOMIAS | K4: DISPONÍVEL | N4: =IF(K5>1000,"🤑",IF(K5>=0,"🐷","😰")) | T4: Entradas | U4: =D29
B5: =D29 | E5: =G29+J29 | H5: =M29 | K5: =D29-G29-J29-M29 | T5: Contas Fixas | U5: =G29
T6: Desp. Variáveis | U6: =J29
N7: =IF(K5>1000,"Cofrinho tá cheio! 💰",IF(K5>=0,"No azul — de olho nos gastos 👀","Ops! Gastou mais do que ganhou 😥")) | T7: Economias | U7: =M29
B10: 💰 Entradas | E10: 🏠 Contas Fixas | H10: 🛒 Despesas Variáveis | K10: 💎 Economias | T10: Entradas | U10: =B5
B11: Nome | C11: Dia | D11: Valor | E11: Nome | F11: Dia | G11: Valor | H11: Nome | I11: Dia | J11: Valor | K11: Nome | L11: Dia | M11: Valor | T11: Despesas | U11: =E5
B12: Salário | C12: 5 | D12: 3000 | E12: Aluguel | F12: 10 | G12: 1200 | H12: Supermercado | I12: 20 | J12: 600 | K12: Reserva de emergência | L12: 30 | M12: 400 | T12: Disponível | U12: =K5
B13: Freela / renda extra | C13: 15 | D13: 500 | E13: Internet | F13: 15 | G13: 100 | H13: Farmácia | I13: 12 | J13: 80
B29: TOTAL | D29: =SUM(D12:D28) | E29: TOTAL | G29: =SUM(G12:G28) | H29: TOTAL | J29: =SUM(J12:J28) | K29: TOTAL | M29: =SUM(M12:M28)

Sheet Outubro
B2: 🐷 Estúdio Planifica • Outubro | T2: ▼ dados dos gráficos (não apague)
B4: ENTRADAS TOTAIS | E4: DESPESAS TOTAIS | H4: ECONOMIAS | K4: DISPONÍVEL | N4: =IF(K5>1000,"🤑",IF(K5>=0,"🐷","😰")) | T4: Entradas | U4: =D29
B5: =D29 | E5: =G29+J29 | H5: =M29 | K5: =D29-G29-J29-M29 | T5: Contas Fixas | U5: =G29
T6: Desp. Variáveis | U6: =J29
N7: =IF(K5>1000,"Cofrinho tá cheio! 💰",IF(K5>=0,"No azul — de olho nos gastos 👀","Ops! Gastou mais do que ganhou 😥")) | T7: Economias | U7: =M29
B10: 💰 Entradas | E10: 🏠 Contas Fixas | H10: 🛒 Despesas Variáveis | K10: 💎 Economias | T10: Entradas | U10: =B5
B11: Nome | C11: Dia | D11: Valor | E11: Nome | F11: Dia | G11: Valor | H11: Nome | I11: Dia | J11: Valor | K11: Nome | L11: Dia | M11: Valor | T11: Despesas | U11: =E5
B12: Salário | C12: 5 | D12: 3000 | E12: Aluguel | F12: 10 | G12: 1200 | H12: Supermercado | I12: 20 | J12: 600 | K12: Reserva de emergência | L12: 30 | M12: 400 | T12: Disponível | U12: =K5
B13: Freela / renda extra | C13: 15 | D13: 500 | E13: Internet | F13: 15 | G13: 100 | H13: Farmácia | I13: 12 | J13: 80
B29: TOTAL | D29: =SUM(D12:D28) | E29: TOTAL | G29: =SUM(G12:G28) | H29: TOTAL | J29: =SUM(J12:J28) | K29: TOTAL | M29: =SUM(M12:M28)

Sheet Novembro
B2: 🐷 Estúdio Planifica • Novembro | T2: ▼ dados dos gráficos (não apague)
B4: ENTRADAS TOTAIS | E4: DESPESAS TOTAIS | H4: ECONOMIAS | K4: DISPONÍVEL | N4: =IF(K5>1000,"🤑",IF(K5>=0,"🐷","😰")) | T4: Entradas | U4: =D29
B5: =D29 | E5: =G29+J29 | H5: =M29 | K5: =D29-G29-J29-M29 | T5: Contas Fixas | U5: =G29
T6: Desp. Variáveis | U6: =J29
N7: =IF(K5>1000,"Cofrinho tá cheio! 💰",IF(K5>=0,"No azul — de olho nos gastos 👀","Ops! Gastou mais do que ganhou 😥")) | T7: Economias | U7: =M29
B10: 💰 Entradas | E10: 🏠 Contas Fixas | H10: 🛒 Despesas Variáveis | K10: 💎 Economias | T10: Entradas | U10: =B5
B11: Nome | C11: Dia | D11: Valor | E11: Nome | F11: Dia | G11: Valor | H11: Nome | I11: Dia | J11: Valor | K11: Nome | L11: Dia | M11: Valor | T11: Despesas | U11: =E5
B12: Salário | C12: 5 | D12: 3000 | E12: Aluguel | F12: 10 | G12: 1200 | H12: Supermercado | I12: 20 | J12: 600 | K12: Reserva de emergência | L12: 30 | M12: 400 | T12: Disponível | U12: =K5
B13: Freela / renda extra | C13: 15 | D13: 500 | E13: Internet | F13: 15 | G13: 100 | H13: Farmácia | I13: 12 | J13: 80
B29: TOTAL | D29: =SUM(D12:D28) | E29: TOTAL | G29: =SUM(G12:G28) | H29: TOTAL | J29: =SUM(J12:J28) | K29: TOTAL | M29: =SUM(M12:M28)

Sheet Dezembro
B2: 🐷 Estúdio Planifica • Dezembro | T2: ▼ dados dos gráficos (não apague)
B4: ENTRADAS TOTAIS | E4: DESPESAS TOTAIS | H4: ECONOMIAS | K4: DISPONÍVEL | N4: =IF(K5>1000,"🤑",IF(K5>=0,"🐷","😰")) | T4: Entradas | U4: =D29
B5: =D29 | E5: =G29+J29 | H5: =M29 | K5: =D29-G29-J29-M29 | T5: Contas Fixas | U5: =G29
T6: Desp. Variáveis | U6: =J29
N7: =IF(K5>1000,"Cofrinho tá cheio! 💰",IF(K5>=0,"No azul — de olho nos gastos 👀","Ops! Gastou mais do que ganhou 😥")) | T7: Economias | U7: =M29
B10: 💰 Entradas | E10: 🏠 Contas Fixas | H10: 🛒 Despesas Variáveis | K10: 💎 Economias | T10: Entradas | U10: =B5
B11: Nome | C11: Dia | D11: Valor | E11: Nome | F11: Dia | G11: Valor | H11: Nome | I11: Dia | J11: Valor | K11: Nome | L11: Dia | M11: Valor | T11: Despesas | U11: =E5
B12: Salário | C12: 5 | D12: 3000 | E12: Aluguel | F12: 10 | G12: 1200 | H12: Supermercado | I12: 20 | J12: 600 | K12: Reserva de emergência | L12: 30 | M12: 400 | T12: Disponível | U12: =K5
B13: Freela / renda extra | C13: 15 | D13: 500 | E13: Internet | F13: 15 | G13: 100 | H13: Farmácia | I13: 12 | J13: 80
B29: TOTAL | D29: =SUM(D12:D28) | E29: TOTAL | G29: =SUM(G12:G28) | H29: TOTAL | J29: =SUM(J12:J28) | K29: TOTAL | M29: =SUM(M12:M28)

Sheet 📅 Resumo do Ano
B2: 📅 Resumo do Ano — Estúdio Planifica
B4: Mês | C4: Entradas | D4: Despesas | E4: Economias | F4: Disponível
B5: Janeiro | C5: ='Janeiro'!B5 | D5: ='Janeiro'!E5 | E5: ='Janeiro'!H5 | F5: ='Janeiro'!K5
B6: Fevereiro | C6: ='Fevereiro'!B5 | D6: ='Fevereiro'!E5 | E6: ='Fevereiro'!H5 | F6: ='Fevereiro'!K5
B7: Março | C7: ='Março'!B5 | D7: ='Março'!E5 | E7: ='Março'!H5 | F7: ='Março'!K5
B8: Abril | C8: ='Abril'!B5 | D8: ='Abril'!E5 | E8: ='Abril'!H5 | F8: ='Abril'!K5
B9: Maio | C9: ='Maio'!B5 | D9: ='Maio'!E5 | E9: ='Maio'!H5 | F9: ='Maio'!K5
B10: Junho | C10: ='Junho'!B5 | D10: ='Junho'!E5 | E10: ='Junho'!H5 | F10: ='Junho'!K5
B11: Julho | C11: ='Julho'!B5 | D11: ='Julho'!E5 | E11: ='Julho'!H5 | F11: ='Julho'!K5
B12: Agosto | C12: ='Agosto'!B5 | D12: ='Agosto'!E5 | E12: ='Agosto'!H5 | F12: ='Agosto'!K5
B13: Setembro | C13: ='Setembro'!B5 | D13: ='Setembro'!E5 | E13: ='Setembro'!H5 | F13: ='Setembro'!K5
B14: Outubro | C14: ='Outubro'!B5 | D14: ='Outubro'!E5 | E14: ='Outubro'!H5 | F14: ='Outubro'!K5
B15: Novembro | C15: ='Novembro'!B5 | D15: ='Novembro'!E5 | E15: ='Novembro'!H5 | F15: ='Novembro'!K5
B16: Dezembro | C16: ='Dezembro'!B5 | D16: ='Dezembro'!E5 | E16: ='Dezembro'!H5 | F16: ='Dezembro'!K5
B17: TOTAL ANO | C17: =SUM(C5:C16) | D17: =SUM(D5:D16) | E17: =SUM(E5:E16) | F17: =SUM(F5:F16)
